<?xml version="1.0" encoding="UTF-8" ?>
<!DOCTYPE mapper PUBLIC "-//mybatis.org//DTD Mapper 3.0//EN" "http://mybatis.org/dtd/mybatis-3-mapper.dtd" >
<mapper namespace="com.jrwp.payMent.dao.HotelUpdateMapper">
    <resultMap id="BaseResultMap" type="com.jrwp.payMent.entity.HotelUpdate">
        <!--
          WARNING - @mbggenerated
          This element is automatically generated by MyBatis Generator, do not modify.
        -->
        <id column="ID" property="id" jdbcType="DECIMAL"/>
        <result column="UPLOADNAME" property="uploadname" jdbcType="OTHER"/>
        <result column="DLLNAME" property="dllname" jdbcType="OTHER"/>
        <result column="WORKTYPE" property="worktype" jdbcType="DECIMAL"/>
    </resultMap>
    <sql id="Base_Column_List">
        <!--
          WARNING - @mbggenerated
          This element is automatically generated by MyBatis Generator, do not modify.
        -->
        ID, UPLOADNAME, DLLNAME, WORKTYPE
    </sql>
    <select id="list" resultMap="BaseResultMap">
        select
        <include refid="Base_Column_List"/>
        from HOTEL_UPDATE order by  id desc
    </select>
    <select id="selectByPrimaryKey" resultMap="BaseResultMap" parameterType="java.math.BigDecimal">
        <!--
          WARNING - @mbggenerated
          This element is automatically generated by MyBatis Generator, do not modify.
        -->
        select
        <include refid="Base_Column_List"/>
        from HOTEL_UPDATE
        where ID = #{id,jdbcType=DECIMAL}
    </select>
    <delete id="deleteByPrimaryKey" parameterType="java.math.BigDecimal">
        <!--
          WARNING - @mbggenerated
          This element is automatically generated by MyBatis Generator, do not modify.
        -->
        delete from HOTEL_UPDATE
        where ID = #{id,jdbcType=DECIMAL}
    </delete>
    <insert id="insert" parameterType="com.jrwp.payMent.entity.HotelUpdate">
        <!--
          WARNING - @mbggenerated
          This element is automatically generated by MyBatis Generator, do not modify.
        -->
        insert into HOTEL_UPDATE (ID, UPLOADNAME, DLLNAME,
        WORKTYPE)
        values (#{id,jdbcType=DECIMAL}, #{uploadname,jdbcType=OTHER}, #{dllname,jdbcType=OTHER},
        #{worktype,jdbcType=DECIMAL})
    </insert>
    <insert id="insertSelective" parameterType="com.jrwp.payMent.entity.HotelUpdate">
        <!--
          WARNING - @mbggenerated
          This element is automatically generated by MyBatis Generator, do not modify.
        -->
        <selectKey resultType="BigDecimal" order="BEFORE" keyProperty="id">
            SELECT SEQ_HOTEL_UPLOAD.nextval FROM dual
        </selectKey>
        insert into HOTEL_UPDATE
        <trim prefix="(" suffix=")" suffixOverrides=",">
            <if test="id != null">
                ID,
            </if>
            <if test="uploadname != null">
                UPLOADNAME,
            </if>
            <if test="dllname != null">
                DLLNAME,
            </if>
            <if test="worktype != null">
                WORKTYPE,
            </if>
        </trim>
        <trim prefix="values (" suffix=")" suffixOverrides=",">
            <if test="id != null">
                #{id,jdbcType=DECIMAL},
            </if>
            <if test="uploadname != null">
                #{uploadname,jdbcType=OTHER},
            </if>
            <if test="dllname != null">
                #{dllname,jdbcType=OTHER},
            </if>
            <if test="worktype != null">
                #{worktype,jdbcType=DECIMAL},
            </if>
        </trim>
    </insert>
    <update id="updateByPrimaryKeySelective" parameterType="com.jrwp.payMent.entity.HotelUpdate">
        <!--
          WARNING - @mbggenerated
          This element is automatically generated by MyBatis Generator, do not modify.
        -->
        update HOTEL_UPDATE
        <set>
            <if test="uploadname != null">
                UPLOADNAME = #{uploadname,jdbcType=OTHER},
            </if>
            <if test="dllname != null">
                DLLNAME = #{dllname,jdbcType=OTHER},
            </if>
            <if test="worktype != null">
                WORKTYPE = #{worktype,jdbcType=DECIMAL},
            </if>
        </set>
        where ID = #{id,jdbcType=DECIMAL}
    </update>
    <update id="updateByPrimaryKey" parameterType="com.jrwp.payMent.entity.HotelUpdate">
        <!--
          WARNING - @mbggenerated
          This element is automatically generated by MyBatis Generator, do not modify.
        -->
        update HOTEL_UPDATE
        set UPLOADNAME = #{uploadname,jdbcType=OTHER},
        DLLNAME = #{dllname,jdbcType=OTHER},
        WORKTYPE = #{worktype,jdbcType=DECIMAL}
        where ID = #{id,jdbcType=DECIMAL}
    </update>
</mapper>